wexample_migration-0.0.18.dist-info/METADATA
wexample_migration-0.0.18.dist-info/WHEEL
wexample_migration-0.0.18.dist-info/entry_points.txt
wexample_migration/__init__.py
wexample_migration/py.typed
wexample_migration-0.0.18.dist-info/RECORD
